wcfg
