Metadata-Version: 1.1
Name: wcfg
Version: 6
Summary: Parser for hyerarchical text data and configuration files
Home-page: https://github.com/aperezdc/python-wcfg
Author: Adrian Perez de Castro
Author-email: aperez@igalia.com
License: Dual GPL3 / MIT
Platform: UNKNOWN
Classifier: Development Status :: 4 - Beta
Classifier: Intended Audience :: Developers
Classifier: Natural Language :: English
Classifier: License :: OSI Approved :: GNU General Public License v3 (GPLv3)
Classifier: License :: OSI Approved :: MIT License
Classifier: Programming Language :: Python :: 2
Classifier: Programming Language :: Python :: 2.6
Classifier: Programming Language :: Python :: 2.7
Classifier: Programming Language :: Python :: 3
Classifier: Programming Language :: Python :: 3.3
Classifier: Programming Language :: Python :: 3.4
Classifier: Programming Language :: Python
Classifier: Operating System :: OS Independent
